schemasheets/__init__.py
schemasheets/conf/configschema.py
schemasheets/conf/configschema.yaml
schemasheets/generate_populate.py
schemasheets/schema_exporter.py
schemasheets/schemamaker.py
schemasheets/schemasheet_datamodel.py
schemasheets/sheets_to_project.py
schemasheets/utils/__init__.py
schemasheets/utils/configschema.py
schemasheets/utils/google_sheets.py
schemasheets/utils/prefixtool.py
schemasheets-0.4.0.dist-info/METADATA
schemasheets-0.4.0.dist-info/WHEEL
schemasheets-0.4.0.dist-info/entry_points.txt
schemasheets-0.4.0.dist-info/RECORD
