Metadata-Version: 2.3
Name: schemasheets
Version: 0.4.0
Summary: Package to author schemas using spreadsheets
Author: cmungall
Author-email: cjm@berkeleybop.org
Requires-Python: >=3.9,<4.0
Classifier: Programming Language :: Python :: 3
Classifier: Programming Language :: Python :: 3.9
Classifier: Programming Language :: Python :: 3.10
Classifier: Programming Language :: Python :: 3.11
Classifier: Programming Language :: Python :: 3.12
Classifier: Programming Language :: Python :: 3.13
Requires-Dist: Jinja2 (>=3.0.3)
Requires-Dist: bioregistry (>0.5.0)
Requires-Dist: linkml (>=1.5.0)
Requires-Dist: linkml-runtime (>=1.5.0)
Requires-Dist: ontodev-cogs (>=0.3.3,<0.4.0)
Project-URL: Documentation, https://github.com/linkml/schemasheets
Project-URL: Homepage, https://github.com/linkml/schemasheets
Project-URL: Repository, https://github.com/linkml/schemasheets
